drfaster/__init__.py
drfaster/dateToInt/__init__.py
drfaster/dateToInt/date_to_int_wrapper.cpython-37m-x86_64-linux-gnu.so
drfaster/centroid_histogram/histogram_wrapper.cpython-37m-x86_64-linux-gnu.so
drfaster/centroid_histogram/__init__.py
drfaster/intToTime/__init__.py
drfaster/intToTime/int2time_wrapper.cpython-37m-x86_64-linux-gnu.so
drfaster-9.0.0.dist-info/METADATA
drfaster-9.0.0.dist-info/top_level.txt
drfaster-9.0.0.dist-info/WHEEL
drfaster-9.0.0.dist-info/RECORD
