Metadata-Version: 2.1
Name: drfaster
Version: 9.0.0
Summary: python library to make performance improvements to the DataRobot repo
Author: DataRobot
Author-email: info@datarobot.com
License: MIT
Classifier: Programming Language :: Python :: 2.7
Classifier: Programming Language :: Python :: 3.6
Classifier: Programming Language :: Python :: 3.7
